pyride_remote_simple/__init__.py
pyride_remote_simple/pyride_remote_simple.py
pyride_remote_simple-0.2.dist-info/DESCRIPTION.rst
pyride_remote_simple-0.2.dist-info/METADATA
pyride_remote_simple-0.2.dist-info/RECORD
pyride_remote_simple-0.2.dist-info/WHEEL
pyride_remote_simple-0.2.dist-info/metadata.json
pyride_remote_simple-0.2.dist-info/top_level.txt
