Metadata-Version: 2.0
Name: pyride-remote-simple
Version: 0.2
Summary: Pure python PyRIDE online remote client
Home-page: https://github.com/uts-magic-lab/pyride_remote_simple
Author: Sammy Pfeiffer
Author-email: Sammy.Pfeiffer@student.uts.edu.au
License: BSD
Platform: UNKNOWN
